smalldict/__init__.py
smalldict/smalldict.py
smalldict-0.1.0.dist-info/LICENSE
smalldict-0.1.0.dist-info/METADATA
smalldict-0.1.0.dist-info/WHEEL
smalldict-0.1.0.dist-info/top_level.txt
smalldict-0.1.0.dist-info/RECORD
